albanianlanguage/__init__.py
albanianlanguage/__version__.py
albanianlanguage/words.py
albanianlanguage/data/words.csv
albanianlanguage-0.1.8.dist-info/licenses/LICENSE
tests/__init__.py
tests/test_words.py
albanianlanguage-0.1.8.dist-info/METADATA
albanianlanguage-0.1.8.dist-info/WHEEL
albanianlanguage-0.1.8.dist-info/top_level.txt
albanianlanguage-0.1.8.dist-info/RECORD
