Metadata-Version: 2.4
Name: albanianlanguage
Version: 0.1.8
Summary: A comprehensive package for the Albanian language processing
Home-page: http://github.com/florijanqosja/albanianlanguage
Author: Florijan Qosja
Author-email: florijanqosja@gmail.com
License: MIT
Project-URL: Bug Tracker, https://github.com/florijanqosja/albanianlanguage/issues
Project-URL: Documentation, https://github.com/florijanqosja/albanianlanguage
Project-URL: Source Code, https://github.com/florijanqosja/albanianlanguage
Keywords: albanian,nlp,language-processing,linguistics
Classifier: Development Status :: 4 - Beta
Classifier: Intended Audience :: Developers
Classifier: Intended Audience :: Science/Research
Classifier: Operating System :: OS Independent
Classifier: Programming Language :: Python :: 3
Classifier: Programming Language :: Python :: 3.8
Classifier: Programming Language :: Python :: 3.9
Classifier: Programming Language :: Python :: 3.10
Classifier: Programming Language :: Python :: 3.11
Classifier: Topic :: Scientific/Engineering :: Artificial Intelligence
Classifier: Topic :: Text Processing :: Linguistic
Classifier: Topic :: Software Development :: Libraries :: Python Modules
Requires-Python: >=3.8
License-File: LICENSE
Dynamic: author
Dynamic: author-email
Dynamic: classifier
Dynamic: description
Dynamic: description-content-type
Dynamic: home-page
Dynamic: keywords
Dynamic: license
Dynamic: license-file
Dynamic: project-url
Dynamic: requires-python
Dynamic: summary
